deep_organizer/__init__.py
deep_organizer/cli.py
deep_organizer/core.py
deep_organizer-1.0.0.dist-info/licenses/LICENSE
deep_organizer-1.0.0.dist-info/METADATA
deep_organizer-1.0.0.dist-info/WHEEL
deep_organizer-1.0.0.dist-info/entry_points.txt
deep_organizer-1.0.0.dist-info/top_level.txt
deep_organizer-1.0.0.dist-info/RECORD
