Metadata-Version: 2.4
Name: deep-organizer
Version: 1.0.0
Summary: AI-powered file organization tool that intelligently organizes files based on content analysis
Home-page: https://github.com/yourusername/deep-organizer
Author: Deep Organizer
Author-email: 
License: MIT
Project-URL: Homepage, https://github.com/yourusername/deep-organizer
Project-URL: Bug Reports, https://github.com/yourusername/deep-organizer/issues
Project-URL: Source, https://github.com/yourusername/deep-organizer
Project-URL: Documentation, https://github.com/yourusername/deep-organizer#readme
Keywords: ai,file-organization,automation,cli,productivity,file-management,langchain,openai,gpt
Classifier: Development Status :: 4 - Beta
Classifier: Intended Audience :: End Users/Desktop
Classifier: Intended Audience :: Developers
Classifier: Topic :: System :: Filesystems
Classifier: Topic :: Utilities
Classifier: License :: OSI Approved :: MIT License
Classifier: Programming Language :: Python :: 3
Classifier: Programming Language :: Python :: 3.8
Classifier: Programming Language :: Python :: 3.9
Classifier: Programming Language :: Python :: 3.10
Classifier: Programming Language :: Python :: 3.11
Classifier: Programming Language :: Python :: 3.12
Classifier: Operating System :: OS Independent
Requires-Python: >=3.8
License-File: LICENSE
Requires-Dist: langgraph
Requires-Dist: langchain[anthropic]
Requires-Dist: python-dotenv
Provides-Extra: dev
Requires-Dist: pytest>=7.0.0; extra == "dev"
Requires-Dist: pytest-cov>=4.0.0; extra == "dev"
Requires-Dist: black>=22.0.0; extra == "dev"
Requires-Dist: isort>=5.10.0; extra == "dev"
Requires-Dist: flake8>=5.0.0; extra == "dev"
Requires-Dist: mypy>=0.991; extra == "dev"
Dynamic: home-page
Dynamic: license-file
Dynamic: requires-python
